ml_unleash/__init__.py
ml_unleash/dockerbuilder.py
ml_unleash-1.1.0.3.dist-info/METADATA
ml_unleash-1.1.0.3.dist-info/WHEEL
ml_unleash-1.1.0.3.dist-info/top_level.txt
ml_unleash-1.1.0.3.dist-info/RECORD
