Metadata-Version: 2.1
Name: ml-unleash
Version: 1.1.0.3
Summary: Package and run machine learning models as docker containers.
Home-page: UNKNOWN
Author: Dwayne Thomson
Author-email: dwaynethomson14@gmail.com
License: UNKNOWN
Keywords: python,docker,mlops
Platform: UNKNOWN
Classifier: Development Status :: 3 - Alpha
Classifier: Intended Audience :: Education
Classifier: Programming Language :: Python :: 2
Classifier: Programming Language :: Python :: 3
Classifier: Operating System :: Microsoft :: Windows
Requires-Dist: Flask
